pictora/__init__.py
pictora/__main__.py
pictora-1.0.7.dist-info/METADATA
pictora-1.0.7.dist-info/WHEEL
pictora-1.0.7.dist-info/entry_points.txt
pictora-1.0.7.dist-info/licenses/LICENSE
pictora-1.0.7.dist-info/RECORD
