Metadata-Version: 2.4
Name: pictora
Version: 1.0.7
Summary: AI-powered local image management and organization tool
Author-email: Dave Lee <dream@fun-coding.org>
License-File: LICENSE
Keywords: ai,image,management,mcp,organization,processing
Classifier: Development Status :: 5 - Production/Stable
Classifier: Intended Audience :: Developers
Classifier: License :: OSI Approved :: MIT License
Classifier: Operating System :: OS Independent
Classifier: Programming Language :: Python :: 3
Classifier: Topic :: Multimedia :: Graphics
Classifier: Topic :: Scientific/Engineering :: Artificial Intelligence
Classifier: Topic :: Software Development :: Libraries :: Python Modules
Requires-Python: >=3.12
Requires-Dist: mcp[cli]>=1.6.0
Requires-Dist: pillow>=11.2.1
